bilm/__init__.py
bilm/data.py
bilm/elmo.py
bilm/model.py
bilm/training.py
bilm-0.1.post5.dist-info/METADATA
bilm-0.1.post5.dist-info/RECORD
bilm-0.1.post5.dist-info/WHEEL
bilm-0.1.post5.dist-info/top_level.txt
